tide/__init__.py
tide/action.py
tide/action_base.py
tide/actionable_dict.py
tide/command_action.py
tide/command_handler.py
tide/command_output.py
tide/command_process.py
tide/config.py
tide/config_command.py
tide/config_command_item.py
tide/config_source.py
tide/editor_base.py
tide/editor_wrapper.py
tide/filter.py
tide/filter_predicate_base.py
tide/interpolate.py
tide/lib_paths.py
tide/log.py
tide/logging_decorator.py
tide/path_helpers.py
tide/singleton.py
tide/tide.py
tide/defaults/__init__.py
tide/defaults/config_location.yaml
tide/defaults/default_config.yaml
tide/defaults/actions/__init__.py
tide/defaults/actions/display_template.py
tide/defaults/actions/get_current_buffer_line.py
tide/defaults/actions/get_current_buffer_name.py
tide/defaults/actions/print_debug.py
tide/defaults/actions/run_command.py
tide/defaults/actions/run_command_string.py
tide/defaults/actions/run_command_with_match.py
tide/defaults/actions/run_config_command.py
tide/defaults/actions/run_python_function.py
tide/defaults/actions/run_vim_function.py
tide/defaults/actions/set_buffer.py
tide/defaults/actions/set_var.py
tide/defaults/editor_wrappers/__init__.py
tide/defaults/editor_wrappers/test_mock.py
tide/defaults/editor_wrappers/vim81.py
tide/defaults/filters/__init__.py
tide/defaults/filters/vg_base.py
tide/defaults/filters/vg_session_log.py
tide/defaults/functions/__init__.py
tide/defaults/templates/__init__.py
tide-0.1.81.dist-info/LICENSE.txt
tide-0.1.81.dist-info/METADATA
tide-0.1.81.dist-info/RECORD
tide-0.1.81.dist-info/WHEEL
tide-0.1.81.dist-info/entry_points.txt
tide-0.1.81.dist-info/top_level.txt
