Metadata-Version: 2.1
Name: tide
Version: 0.1.81
Summary: From text editor to Integrated Development Environment. This allows you to use a yaml config and some scripting to deliver cross-platform, cross-editor plugins.
Home-page: https://github.com/wilvk/tide
Author: Willem van Ketwich
Author-email: willvk@gmail.com
License: MIT
Download-URL: https://github.com/wilvk/tide/archive/0.1.tar.gz
Keywords: editor,configuration
Platform: UNKNOWN
Classifier: Development Status :: 3 - Alpha
Classifier: Intended Audience :: Developers
Classifier: Natural Language :: English
Classifier: Topic :: Software Development
Classifier: Topic :: Text Editors
Classifier: Topic :: Text Processing
Classifier: Programming Language :: Python :: 3
Classifier: Operating System :: OS Independent
Classifier: Intended Audience :: Information Technology
Classifier: License :: OSI Approved :: GNU General Public License v3 or later (GPLv3+)
Requires-Python: >=3.4
Provides-Extra: test
Provides-Extra: dev
Requires-Dist: jinja2
Requires-Dist: markupsafe
Requires-Dist: pexpect
Requires-Dist: ptyprocess
Requires-Dist: pyyaml
Requires-Dist: six
Requires-Dist: yamlreader
Provides-Extra: dev
Provides-Extra: test
Requires-Dist: nose; extra == 'test'
